{
  "category": "rescue",
  "items": [
    {
      "id": "ff_radio",
      "weight_g": 350,
      "volume_cm3": 200,
      "dual_use": false,
      "hazard_flag": false,
      "sources": [
        {
          "title": "消防装備基準"
        }
      ],
      "scores": {
        "survivability": 2,
        "signalability": 3,
        "exfiltration_support": 0,
        "concealability": 1,
        "legality_penalty": 0
      },
      "name_ja": "業務用無線機",
      "name_en": "Professional Radio",
      "category_ja": "通信",
      "category_en": "Communications",
      "purpose_short_ja": "指令室・隊員間通信",
      "purpose_short_en": "Command center and team communication",
      "legality_notes_ja": {
        "JP": "業務用途のみ"
      },
      "legality_notes_en": {
        "JP": "Professional use only"
      },
      "description_ja": "",
      "description_en": ""
    },
    {
      "id": "ff_flashlight",
      "weight_g": 200,
      "volume_cm3": 150,
      "dual_use": false,
      "hazard_flag": false,
      "sources": [
        {
          "title": "消防装備基準"
        }
      ],
      "scores": {
        "survivability": 3,
        "signalability": 1,
        "exfiltration_support": 0,
        "concealability": 1,
        "legality_penalty": 0
      },
      "name_ja": "防爆ライト",
      "name_en": "Explosion-proof Light",
      "category_ja": "工具",
      "category_en": "Tools",
      "purpose_short_ja": "暗所・煙中での視界確保",
      "purpose_short_en": "Visibility in darkness and smoke",
      "legality_notes_ja": {
        "JP": "許可"
      },
      "legality_notes_en": {
        "JP": "Allowed"
      },
      "description_ja": "",
      "description_en": ""
    },
    {
      "id": "ff_gloves",
      "weight_g": 250,
      "volume_cm3": 300,
      "dual_use": false,
      "hazard_flag": false,
      "sources": [
        {
          "title": "消防防護服基準"
        }
      ],
      "scores": {
        "survivability": 3,
        "signalability": 0,
        "exfiltration_support": 0,
        "concealability": 1,
        "legality_penalty": 0
      },
      "name_ja": "耐熱手袋",
      "name_en": "Heat-resistant Gloves",
      "category_ja": "その他",
      "category_en": "Other",
      "purpose_short_ja": "高温物への接触保護",
      "purpose_short_en": "Protection from hot objects",
      "legality_notes_ja": {
        "JP": "許可"
      },
      "legality_notes_en": {
        "JP": "Allowed"
      },
      "description_ja": "",
      "description_en": ""
    },
    {
      "id": "ff_axe",
      "weight_g": 1200,
      "volume_cm3": 800,
      "dual_use": true,
      "hazard_flag": true,
      "sources": [
        {
          "title": "消防装備基準"
        }
      ],
      "scores": {
        "survivability": 2,
        "signalability": 0,
        "exfiltration_support": 2,
        "concealability": 0,
        "legality_penalty": 3
      },
      "name_ja": "消防斧",
      "name_en": "Fire Axe",
      "category_ja": "工具",
      "category_en": "Tools",
      "purpose_short_ja": "破壊進入・障害物除去",
      "purpose_short_en": "Forcible entry, obstacle removal",
      "legality_notes_ja": {
        "JP": "業務用途のみ、一般携帯は銃刀法違反の可能性"
      },
      "legality_notes_en": {
        "JP": "Professional use only, civilian carry may violate weapons laws"
      },
      "description_ja": "",
      "description_en": ""
    },
    {
      "id": "ff_rope",
      "weight_g": 800,
      "volume_cm3": 600,
      "dual_use": false,
      "hazard_flag": false,
      "sources": [
        {
          "title": "消防技術基準"
        }
      ],
      "scores": {
        "survivability": 2,
        "signalability": 0,
        "exfiltration_support": 3,
        "concealability": 0,
        "legality_penalty": 0
      },
      "name_ja": "救助ロープ（10m）",
      "name_en": "Rescue Rope (10m)",
      "category_ja": "工具",
      "category_en": "Tools",
      "purpose_short_ja": "要救助者の救出・降下",
      "purpose_short_en": "Victim rescue and descent",
      "legality_notes_ja": {
        "JP": "許可"
      },
      "legality_notes_en": {
        "JP": "Allowed"
      },
      "description_ja": "",
      "description_en": ""
    },
    {
      "id": "ff_mask_spare",
      "weight_g": 150,
      "volume_cm3": 100,
      "dual_use": false,
      "hazard_flag": false,
      "sources": [
        {
          "title": "空気呼吸器保守基準"
        }
      ],
      "scores": {
        "survivability": 3,
        "signalability": 0,
        "exfiltration_support": 0,
        "concealability": 2,
        "legality_penalty": 0
      },
      "name_ja": "予備空気ボンベバルブ",
      "name_en": "Spare Air Tank Valve",
      "category_ja": "その他",
      "category_en": "Other",
      "purpose_short_ja": "SCBA予備部品",
      "purpose_short_en": "SCBA spare parts",
      "legality_notes_ja": {
        "JP": "許可"
      },
      "legality_notes_en": {
        "JP": "Allowed"
      },
      "description_ja": "",
      "description_en": ""
    },
    {
      "id": "ff_water_bottle",
      "weight_g": 150,
      "volume_cm3": 1000,
      "dual_use": false,
      "hazard_flag": false,
      "sources": [
        {
          "title": "消防活動指針"
        }
      ],
      "scores": {
        "survivability": 3,
        "signalability": 0,
        "exfiltration_support": 0,
        "concealability": 1,
        "legality_penalty": 0
      },
      "name_ja": "携帯水筒（1L）",
      "name_en": "Portable Water Bottle (1L)",
      "category_ja": "サバイバル",
      "category_en": "Survival",
      "purpose_short_ja": "脱水防止・長時間活動",
      "purpose_short_en": "Dehydration prevention, extended activity",
      "legality_notes_ja": {
        "JP": "許可"
      },
      "legality_notes_en": {
        "JP": "Allowed"
      },
      "description_ja": "",
      "description_en": ""
    },
    {
      "id": "ff_thermal_camera",
      "weight_g": 500,
      "volume_cm3": 300,
      "dual_use": true,
      "hazard_flag": false,
      "sources": [
        {
          "title": "消防技術"
        }
      ],
      "scores": {
        "survivability": 2,
        "signalability": 0,
        "exfiltration_support": 3,
        "concealability": 1,
        "legality_penalty": 1
      },
      "name_ja": "携帯型熱画像カメラ",
      "name_en": "Portable Thermal Camera",
      "category_ja": "工具",
      "category_en": "Tools",
      "purpose_short_ja": "火点探知・要救助者発見",
      "purpose_short_en": "Fire detection, victim location",
      "legality_notes_ja": {
        "JP": "業務用途推奨"
      },
      "legality_notes_en": {
        "JP": "Professional use recommended"
      },
      "description_ja": "",
      "description_en": ""
    },
    {
      "id": "ff_marker",
      "weight_g": 50,
      "volume_cm3": 30,
      "dual_use": false,
      "hazard_flag": false,
      "sources": [
        {
          "title": "USAR標準"
        }
      ],
      "scores": {
        "survivability": 1,
        "signalability": 2,
        "exfiltration_support": 0,
        "concealability": 3,
        "legality_penalty": 0
      },
      "name_ja": "マーキングチョーク",
      "name_en": "Marking Chalk",
      "category_ja": "その他",
      "category_en": "Other",
      "purpose_short_ja": "捜索済み表示",
      "purpose_short_en": "Searched area marking",
      "legality_notes_ja": {
        "JP": "許可"
      },
      "legality_notes_en": {
        "JP": "Allowed"
      },
      "description_ja": "",
      "description_en": ""
    },
    {
      "id": "ff_multitool",
      "weight_g": 200,
      "volume_cm3": 80,
      "dual_use": true,
      "hazard_flag": false,
      "sources": [
        {
          "title": "消防装備"
        }
      ],
      "scores": {
        "survivability": 2,
        "signalability": 0,
        "exfiltration_support": 1,
        "concealability": 2,
        "legality_penalty": 1
      },
      "name_ja": "消防用マルチツール",
      "name_en": "Fire Service Multitool",
      "category_ja": "工具",
      "category_en": "Tools",
      "purpose_short_ja": "配管・バルブ操作",
      "purpose_short_en": "Pipe and valve operation",
      "legality_notes_ja": {
        "JP": "業務用途のみ"
      },
      "legality_notes_en": {
        "JP": "Professional use only"
      },
      "description_ja": "",
      "description_en": ""
    }
  ],
  "name_ja": "消防隊員型",
  "name_en": "Firefighter"
}